{"acadYear":"2019/2020","description":"The final Design Project for the M (Arch) with a specialization in Design Technology and Management is the culmination of the technical and design learning predicated on the instrumental value of technical design as a means of to a wider agenda of sustainable building, resource conservation and creating positive environmental impacts. Students are expected to demonstrate research in design technology as a basis for addressing emergent and perceived need in the aesthetic, cultural and social field. The use of design as a form of research applied to building infrastructure or the environment relevant to practical design issues in industry. Students are required to produce drawings and models illustrating technical exploration and resolution with digitally aided or lab based experimentation. Projects will be supervised by tutors of students choice assisted by a panel of technical specialists.","title":"Final Design Project","department":"Architecture","faculty":"Design and Environment","workload":[4,4,0,18,34],"moduleCredit":"20","moduleCode":"AR5808","semesterData":[{"semester":1,"timetable":[{"classNo":"19","startTime":"1400","endTime":"1800","weeks":[1,2,3,4,5,6,7,8,9,10,11,12,13],"venue":"","day":"Tuesday","lessonType":"Tutorial","size":10},{"classNo":"17","startTime":"1400","endTime":"1800","weeks":[1,2,3,4,5,6,7,8,9,10,11,12,13],"venue":"","day":"Tuesday","lessonType":"Tutorial","size":10},{"classNo":"29","startTime":"1400","endTime":"1800","weeks":[1,2,3,4,5,6,7,8,9,10,11,12,13],"venue":"","day":"Tuesday","lessonType":"Tutorial","size":10},{"classNo":"21","startTime":"1400","endTime":"1800","weeks":[1,2,3,4,5,6,7,8,9,10,11,12,13],"venue":"","day":"Tuesday","lessonType":"Tutorial","size":10},{"classNo":"26","startTime":"1400","endTime":"1800","weeks":[1,2,3,4,5,6,7,8,9,10,11,12,13],"venue":"","day":"Tuesday","lessonType":"Tutorial","size":10},{"classNo":"28","startTime":"1400","endTime":"1800","weeks":[1,2,3,4,5,6,7,8,9,10,11,12,13],"venue":"","day":"Tuesday","lessonType":"Tutorial","size":10},{"classNo":"20","startTime":"1400","endTime":"1800","weeks":[1,2,3,4,5,6,7,8,9,10,11,12,13],"venue":"","day":"Tuesday","lessonType":"Tutorial","size":10},{"classNo":"22","startTime":"1400","endTime":"1800","weeks":[1,2,3,4,5,6,7,8,9,10,11,12,13],"venue":"","day":"Tuesday","lessonType":"Tutorial","size":10},{"classNo":"24","startTime":"1400","endTime":"1800","weeks":[1,2,3,4,5,6,7,8,9,10,11,12,13],"venue":"","day":"Tuesday","lessonType":"Tutorial","size":10},{"classNo":"11","startTime":"1400","endTime":"1800","weeks":[1,2,3,4,5,6,7,8,9,10,11,12,13],"venue":"","day":"Tuesday","lessonType":"Tutorial","size":10},{"classNo":"2","startTime":"1400","endTime":"1800","weeks":[1,2,3,4,5,6,7,8,9,10,11,12,13],"venue":"","day":"Tuesday","lessonType":"Tutorial","size":10},{"classNo":"37","startTime":"1400","endTime":"1800","weeks":[1,2,3,4,5,6,7,8,9,10,11,12,13],"venue":"","day":"Tuesday","lessonType":"Tutorial","size":10}]},{"semester":2,"timetable":[{"classNo":"36","startTime":"0900","endTime":"1800","weeks":[1,2,3,4,5,6,7,8,9,10,11,12,13],"venue":"","day":"Tuesday","lessonType":"Tutorial","size":10},{"classNo":"29","startTime":"0900","endTime":"1800","weeks":[1,2,3,4,5,6,7,8,9,10,11,12,13],"venue":"","day":"Tuesday","lessonType":"Tutorial","size":10},{"classNo":"37","startTime":"0900","endTime":"1800","weeks":[1,2,3,4,5,6,7,8,9,10,11,12,13],"venue":"","day":"Tuesday","lessonType":"Tutorial","size":10},{"classNo":"20","startTime":"0900","endTime":"1800","weeks":[1,2,3,4,5,6,7,8,9,10,11,12,13],"venue":"","day":"Tuesday","lessonType":"Tutorial","size":10},{"classNo":"18","startTime":"0900","endTime":"1800","weeks":[1,2,3,4,5,6,7,8,9,10,11,12,13],"venue":"","day":"Tuesday","lessonType":"Tutorial","size":10},{"classNo":"2","startTime":"0900","endTime":"1800","weeks":[1,2,3,4,5,6,7,8,9,10,11,12,13],"venue":"","day":"Tuesday","lessonType":"Tutorial","size":10},{"classNo":"24","startTime":"0900","endTime":"1800","weeks":[1,2,3,4,5,6,7,8,9,10,11,12,13],"venue":"","day":"Tuesday","lessonType":"Tutorial","size":10},{"classNo":"25","startTime":"0900","endTime":"1800","weeks":[1,2,3,4,5,6,7,8,9,10,11,12,13],"venue":"","day":"Tuesday","lessonType":"Tutorial","size":10},{"classNo":"6","startTime":"0900","endTime":"1800","weeks":[1,2,3,4,5,6,7,8,9,10,11,12,13],"venue":"","day":"Tuesday","lessonType":"Tutorial","size":10},{"classNo":"15","startTime":"0900","endTime":"1800","weeks":[1,2,3,4,5,6,7,8,9,10,11,12,13],"venue":"","day":"Tuesday","lessonType":"Tutorial","size":10},{"classNo":"38","startTime":"0900","endTime":"1800","weeks":[1,2,3,4,5,6,7,8,9,10,11,12,13],"venue":"","day":"Tuesday","lessonType":"Tutorial","size":10},{"classNo":"5","startTime":"0900","endTime":"1800","weeks":[1,2,3,4,5,6,7,8,9,10,11,12,13],"venue":"","day":"Tuesday","lessonType":"Tutorial","size":10},{"classNo":"7","startTime":"0900","endTime":"1800","weeks":[1,2,3,4,5,6,7,8,9,10,11,12,13],"venue":"","day":"Tuesday","lessonType":"Tutorial","size":10},{"classNo":"8","startTime":"0900","endTime":"1800","weeks":[1,2,3,4,5,6,7,8,9,10,11,12,13],"venue":"","day":"Tuesday","lessonType":"Tutorial","size":10},{"classNo":"9","startTime":"0900","endTime":"1800","weeks":[1,2,3,4,5,6,7,8,9,10,11,12,13],"venue":"","day":"Tuesday","lessonType":"Tutorial","size":10},{"classNo":"10","startTime":"0900","endTime":"1800","weeks":[1,2,3,4,5,6,7,8,9,10,11,12,13],"venue":"","day":"Tuesday","lessonType":"Tutorial","size":10},{"classNo":"11","startTime":"0900","endTime":"1800","weeks":[1,2,3,4,5,6,7,8,9,10,11,12,13],"venue":"","day":"Tuesday","lessonType":"Tutorial","size":10},{"classNo":"12","startTime":"0900","endTime":"1800","weeks":[1,2,3,4,5,6,7,8,9,10,11,12,13],"venue":"","day":"Tuesday","lessonType":"Tutorial","size":10},{"classNo":"13","startTime":"0900","endTime":"1800","weeks":[1,2,3,4,5,6,7,8,9,10,11,12,13],"venue":"","day":"Tuesday","lessonType":"Tutorial","size":10},{"classNo":"14","startTime":"0900","endTime":"1800","weeks":[1,2,3,4,5,6,7,8,9,10,11,12,13],"venue":"","day":"Tuesday","lessonType":"Tutorial","size":10},{"classNo":"28","startTime":"0900","endTime":"1800","weeks":[1,2,3,4,5,6,7,8,9,10,11,12,13],"venue":"","day":"Tuesday","lessonType":"Tutorial","size":10},{"classNo":"3","startTime":"0900","endTime":"1800","weeks":[1,2,3,4,5,6,7,8,9,10,11,12,13],"venue":"","day":"Tuesday","lessonType":"Tutorial","size":10},{"classNo":"30","startTime":"0900","endTime":"1800","weeks":[1,2,3,4,5,6,7,8,9,10,11,12,13],"venue":"","day":"Tuesday","lessonType":"Tutorial","size":10},{"classNo":"31","startTime":"0900","endTime":"1800","weeks":[1,2,3,4,5,6,7,8,9,10,11,12,13],"venue":"","day":"Tuesday","lessonType":"Tutorial","size":10},{"classNo":"33","startTime":"0900","endTime":"1800","weeks":[1,2,3,4,5,6,7,8,9,10,11,12,13],"venue":"","day":"Tuesday","lessonType":"Tutorial","size":10},{"classNo":"34","startTime":"0900","endTime":"1800","weeks":[1,2,3,4,5,6,7,8,9,10,11,12,13],"venue":"","day":"Tuesday","lessonType":"Tutorial","size":10},{"classNo":"16","startTime":"0900","endTime":"1800","weeks":[1,2,3,4,5,6,7,8,9,10,11,12,13],"venue":"","day":"Tuesday","lessonType":"Tutorial","size":10},{"classNo":"17","startTime":"0900","endTime":"1800","weeks":[1,2,3,4,5,6,7,8,9,10,11,12,13],"venue":"","day":"Tuesday","lessonType":"Tutorial","size":10},{"classNo":"19","startTime":"0900","endTime":"1800","weeks":[1,2,3,4,5,6,7,8,9,10,11,12,13],"venue":"","day":"Tuesday","lessonType":"Tutorial","size":10},{"classNo":"21","startTime":"0900","endTime":"1800","weeks":[1,2,3,4,5,6,7,8,9,10,11,12,13],"venue":"","day":"Tuesday","lessonType":"Tutorial","size":10},{"classNo":"22","startTime":"0900","endTime":"1800","weeks":[1,2,3,4,5,6,7,8,9,10,11,12,13],"venue":"","day":"Tuesday","lessonType":"Tutorial","size":10},{"classNo":"23","startTime":"0900","endTime":"1800","weeks":[1,2,3,4,5,6,7,8,9,10,11,12,13],"venue":"","day":"Tuesday","lessonType":"Tutorial","size":10},{"classNo":"26","startTime":"0900","endTime":"1800","weeks":[1,2,3,4,5,6,7,8,9,10,11,12,13],"venue":"","day":"Tuesday","lessonType":"Tutorial","size":10},{"classNo":"1","startTime":"0900","endTime":"1800","weeks":[1,2,3,4,5,6,7,8,9,10,11,12,13],"venue":"","day":"Tuesday","lessonType":"Design Lecture","size":150},{"classNo":"1","startTime":"0900","endTime":"1800","weeks":[1,2,3,4,5,6,7,8,9,10,11,12,13],"venue":"","day":"Tuesday","lessonType":"Tutorial","size":10},{"classNo":"32","startTime":"0900","endTime":"1800","weeks":[1,2,3,4,5,6,7,8,9,10,11,12,13],"venue":"","day":"Tuesday","lessonType":"Tutorial","size":10},{"classNo":"35","startTime":"0900","endTime":"1800","weeks":[1,2,3,4,5,6,7,8,9,10,11,12,13],"venue":"","day":"Tuesday","lessonType":"Tutorial","size":10},{"classNo":"27","startTime":"0900","endTime":"1800","weeks":[1,2,3,4,5,6,7,8,9,10,11,12,13],"venue":"","day":"Tuesday","lessonType":"Tutorial","size":10}]}]}
