{"acadYear":"2019/2020","description":"This academic orientation module for Microsoft Excel equips students with basic spreadsheet knowledge for the BBA and BBA (Accountancy) curriculum.","title":"Microsoft Excel Skills for Business","department":"Analytics and Operations","faculty":"NUS Business School","moduleCredit":"0","moduleCode":"BPM1702","semesterData":[{"semester":1,"timetable":[{"classNo":"A2","startTime":"1801","endTime":"1802","weeks":[1],"venue":"LT16","day":"Saturday","lessonType":"Sectional Teaching","size":300},{"classNo":"A1","startTime":"1800","endTime":"1801","weeks":[1],"venue":"LT16","day":"Saturday","lessonType":"Sectional Teaching","size":900}]}]}
