{"acadYear":"2019/2020","preclusion":"BSP1004; BSP1004X; RE1703","description":"This course will equip business students with basic legal knowledge relating to commercial transactions so that they will be more aware of potential legal problems which may arise in the course of business and having become aware, to have recourse to such professional legal advice as is necessary in the circumstances. Subjects that meet these requirements include the Singapore Legal System, mediation and arbitration to resolve disputes, the types of various business organisations for businesses to conduct effectively within the law, directors' duties & liabilities, the making of valid business contracts and the rights & obligations of traders in the market place and negligence in the business environment through misstatements.","title":"Legal Environment of Business","department":"Strategy and Policy","faculty":"NUS Business School","workload":[0,3,0,3,4],"moduleCredit":"4","moduleCode":"BSP1702","attributes":{"su":true,"ssgf":true},"semesterData":[{"semester":1,"timetable":[{"classNo":"A10","startTime":"1500","endTime":"1800","weeks":[1,2,3,4,5,6,7,8,9,10,11,12,13],"venue":"BIZ1-0203","day":"Friday","lessonType":"Sectional Teaching","size":55},{"classNo":"A11","startTime":"1500","endTime":"1800","weeks":[1,2,3,4,5,6,7,8,9,10,11,12,13],"venue":"BIZ1-0206","day":"Friday","lessonType":"Sectional Teaching","size":55},{"classNo":"A1","startTime":"1500","endTime":"1800","weeks":[1,2,3,4,5,6,7,8,9,10,11,12,13],"venue":"BIZ1-0203","day":"Thursday","lessonType":"Sectional Teaching","size":55},{"classNo":"A7","startTime":"0830","endTime":"1130","weeks":[1,2,3,4,5,6,7,8,9,10,11,12,13],"venue":"BIZ1-0203","day":"Friday","lessonType":"Sectional Teaching","size":55},{"classNo":"A4","startTime":"0830","endTime":"1130","weeks":[1,2,3,4,5,6,7,8,9,10,11,12,13],"venue":"BIZ2-0509","day":"Friday","lessonType":"Sectional Teaching","size":55},{"classNo":"A3","startTime":"1500","endTime":"1800","weeks":[1,2,3,4,5,6,7,8,9,10,11,12,13],"venue":"BIZ1-0201","day":"Friday","lessonType":"Sectional Teaching","size":55},{"classNo":"A8","startTime":"1500","endTime":"1800","weeks":[1,2,3,4,5,6,7,8,9,10,11,12,13],"venue":"BIZ1-0206","day":"Thursday","lessonType":"Sectional Teaching","size":55},{"classNo":"A9","startTime":"0830","endTime":"1130","weeks":[1,2,3,4,5,6,7,8,9,10,11,12,13],"venue":"BIZ1-0305","day":"Friday","lessonType":"Sectional Teaching","size":55},{"classNo":"A6","startTime":"0830","endTime":"1130","weeks":[1,2,3,4,5,6,7,8,9,10,11,12,13],"venue":"HSSMLCR","day":"Thursday","lessonType":"Sectional Teaching","size":55},{"classNo":"A2","startTime":"0830","endTime":"1130","weeks":[1,2,3,4,5,6,7,8,9,10,11,12,13],"venue":"BIZ1-0205","day":"Thursday","lessonType":"Sectional Teaching","size":55},{"classNo":"A5","startTime":"1500","endTime":"1800","weeks":[1,2,3,4,5,6,7,8,9,10,11,12,13],"venue":"HSSMLCR","day":"Thursday","lessonType":"Sectional Teaching","size":55}],"examDate":"2019-11-30T01:00:00.000Z","examDuration":60},{"semester":2,"timetable":[{"classNo":"A9","startTime":"1500","endTime":"1800","weeks":[1,2,3,4,5,6,7,8,9,10,11,12,13],"venue":"BIZ1-0203","day":"Friday","lessonType":"Sectional Teaching","size":50},{"classNo":"A4","startTime":"1500","endTime":"1800","weeks":[1,2,3,4,5,6,7,8,9,10,11,12,13],"venue":"BIZ2-0509","day":"Thursday","lessonType":"Sectional Teaching","size":50},{"classNo":"A5","startTime":"0830","endTime":"1130","weeks":[1,2,3,4,5,6,7,8,9,10,11,12,13],"venue":"BIZ1-0203","day":"Friday","lessonType":"Sectional Teaching","size":50},{"classNo":"A6","startTime":"0830","endTime":"1130","weeks":[1,2,3,4,5,6,7,8,9,10,11,12,13],"venue":"BIZ1-0204","day":"Friday","lessonType":"Sectional Teaching","size":50},{"classNo":"A7","startTime":"0830","endTime":"1130","weeks":[1,2,3,4,5,6,7,8,9,10,11,12,13],"venue":"BIZ2-0509","day":"Friday","lessonType":"Sectional Teaching","size":50},{"classNo":"A8","startTime":"1500","endTime":"1800","weeks":[1,2,3,4,5,6,7,8,9,10,11,12,13],"venue":"HSSMLCR","day":"Friday","lessonType":"Sectional Teaching","size":50},{"classNo":"A2","startTime":"0830","endTime":"1130","weeks":[1,2,3,4,5,6,7,8,9,10,11,12,13],"venue":"BIZ1-0204","day":"Thursday","lessonType":"Sectional Teaching","size":50},{"classNo":"A11","startTime":"0830","endTime":"1130","weeks":[1,2,3,4,5,6,7,8,9,10,11,12,13],"venue":"BIZ2-0509","day":"Thursday","lessonType":"Sectional Teaching","size":50},{"classNo":"A10","startTime":"1500","endTime":"1800","weeks":[1,2,3,4,5,6,7,8,9,10,11,12,13],"venue":"BIZ1-0206","day":"Friday","lessonType":"Sectional Teaching","size":50},{"classNo":"A1","startTime":"0830","endTime":"1130","weeks":[1,2,3,4,5,6,7,8,9,10,11,12,13],"venue":"HSSMLCR","day":"Thursday","lessonType":"Sectional Teaching","size":50}],"examDate":"2020-04-30T09:00:00.000Z","examDuration":120}],"fulfillRequirements":["ACC3706","ACC3703","ACC3702","BSN4711"]}
