{"acadYear":"2019/2020","description":"Atomic absorption and emission spectrometry; atomic x-ray spectrometry; electron and ion spectrometry; radiochemical methods of analysis; molecular absorption spectrometry and discussions on applications of these techniques, e.g. in environmental analysis, materials analysis, biological tissue analysis, etc.","title":"Instrumental Analysis I","department":"Chemistry","faculty":"Science","workload":[3,1,0,3,3],"prerequisite":"CM2192","moduleCredit":"4","moduleCode":"CM3241","semesterData":[{"semester":2,"timetable":[{"classNo":"1","startTime":"1600","endTime":"1800","weeks":[1,2,3,4,5,6,7,8,9,10,11,12,13],"venue":"S16-0307","day":"Tuesday","lessonType":"Lecture","size":80},{"classNo":"1","startTime":"1600","endTime":"1800","weeks":[1,2,3,4,5,6,7,8,9,10,11,12,13],"venue":"S16-0307","day":"Thursday","lessonType":"Lecture","size":80},{"classNo":"2","startTime":"1700","endTime":"1800","weeks":[1,2,3,4,5,6,7,8,9,10,11,12,13],"venue":"S16-0440","day":"Wednesday","lessonType":"Tutorial","size":27},{"classNo":"1","startTime":"1700","endTime":"1800","weeks":[1,2,3,4,5,6,7,8,9,10,11,12,13],"venue":"S16-0304","day":"Monday","lessonType":"Tutorial","size":26},{"classNo":"3","startTime":"1300","endTime":"1400","weeks":[1,2,3,4,5,6,7,8,9,10,11,12,13],"venue":"S16-0309","day":"Wednesday","lessonType":"Tutorial","size":27}],"examDate":"2020-05-04T01:00:00.000Z","examDuration":120}],"prereqTree":"CM2192"}
