{"acadYear":"2019/2020","preclusion":"GET1027","description":"The first six weeks  we read Plato (a 5th Century BC Greek, of whom it has been said, 'All of Western thought is just footnotes to Plato') and Descartes (a 17th Century Frenchman, of 'I think therefore I am' fame.) The second six weeks concern questions and problems raised by Plato and Descartes. We will mull the metaphysics of mind and consciousness; ponder the politics of freedom. The module title hints at a basic question: what sorts of ways of convincing people, and being convinced by people - about life, about anything - are good ways?","title":"Reason and Persuasion","department":"Philosophy","faculty":"Arts and Social Science","moduleCredit":"4","moduleCode":"GEM1004","attributes":{"su":true},"aliases":["GET1027"],"semesterData":[{"semester":2,"timetable":[{"classNo":"E3","startTime":"0800","endTime":"1000","weeks":[4,6,8,10,12],"venue":"AS3-0302","day":"Wednesday","lessonType":"Tutorial","size":0},{"classNo":"E5","startTime":"1600","endTime":"1800","weeks":[4,6,8,10,12],"venue":"AS4-0604","day":"Wednesday","lessonType":"Tutorial","size":0},{"classNo":"E2","startTime":"1600","endTime":"1800","weeks":[4,6,8,10,12],"venue":"AS1-0211","day":"Monday","lessonType":"Tutorial","size":0},{"classNo":"1","startTime":"0800","endTime":"1000","weeks":[1,2,3,4,5,6,7,8,9,10,11,12,13],"venue":"","day":"Monday","lessonType":"Lecture","size":0},{"classNo":"E1","startTime":"0800","endTime":"1000","weeks":[4,6,8,10,12],"venue":"AS3-0302","day":"Friday","lessonType":"Tutorial","size":0},{"classNo":"E4","startTime":"1600","endTime":"1800","weeks":[4,6,8,10,12],"venue":"AS8-0402","day":"Friday","lessonType":"Tutorial","size":0}]}]}
