{"acadYear":"2019/2020","preclusion":"SSA2205, JS2224","description":"This module aims to promote a better understanding of Singapore-Japan relations, combining historical, political, economic, social and cultural perspectives. Besides an examination of the history of interactions between people in Singapore and Japan from the late 19th century to the present, the module also helps students grasp issues affecting Singapore‘s position and perception in a wider geographical and cultural context by considering its relations with Japan. Students are actively encouraged to use oral history, fieldwork and internet for their projects.","title":"Singapore and Japan: Historical and Contemporary Relationships","department":"Japanese Studies","faculty":"Arts and Social Science","workload":[2,1,0,3,4],"moduleCredit":"4","moduleCode":"GES1015","attributes":{"su":true},"semesterData":[{"semester":2,"timetable":[{"classNo":"E1","startTime":"1000","endTime":"1200","weeks":[4,6,8,10,12],"venue":"AS5-0202","day":"Monday","lessonType":"Tutorial","size":18},{"classNo":"E2","startTime":"1200","endTime":"1400","weeks":[4,6,8,10,12],"venue":"AS1-0302","day":"Monday","lessonType":"Tutorial","size":18},{"classNo":"1","startTime":"1000","endTime":"1200","weeks":[1,2,3,4,5,6,7,8,9,10,11,12,13],"venue":"NAK-AUD","day":"Tuesday","lessonType":"Lecture","size":90},{"classNo":"D2","startTime":"1200","endTime":"1400","weeks":[3,5,7,9,11,13],"venue":"AS3-0302","day":"Monday","lessonType":"Tutorial","size":18},{"classNo":"D1","startTime":"1000","endTime":"1200","weeks":[3,5,7,9,11,13],"venue":"AS3-0306","day":"Monday","lessonType":"Tutorial","size":18},{"classNo":"E3","startTime":"1600","endTime":"1800","weeks":[4,6,8,10,12],"venue":"AS1-0303","day":"Monday","lessonType":"Tutorial","size":18}]}]}
