{"acadYear":"2019/2020","description":"This module will examine the relationship between society and health-related issues. The differing notions of \"illness\" and \"wellness,\" and how societies influence the type, definition and distribution of disease and illness will be examined. The social organization of medicine, the social functions of health-care institutions in society will also be explored. Special emphasis will also be given to the role of the state in providing health-care as well as the relationship between the state and the health industry. This course is mounted for students throughout NUS with interest in society and health-related issues.","title":"Medical Sociology","department":"Sociology","faculty":"Arts and Social Science","workload":[2,1,0,2,5],"moduleCredit":"4","moduleCode":"SC2211","attributes":{"su":true},"semesterData":[{"semester":2,"timetable":[{"classNo":"E3","startTime":"1200","endTime":"1400","weeks":[4,6,8,10,12],"venue":"","day":"Tuesday","lessonType":"Tutorial","size":25},{"classNo":"D3","startTime":"1200","endTime":"1400","weeks":[3,5,7,9,11],"venue":"","day":"Tuesday","lessonType":"Tutorial","size":25},{"classNo":"E6","startTime":"1200","endTime":"1400","weeks":[4,6,8,10,12],"venue":"AS1-0213","day":"Friday","lessonType":"Tutorial","size":25},{"classNo":"E7","startTime":"0800","endTime":"1000","weeks":[4,6,8,10,12],"venue":"AS1-0209","day":"Monday","lessonType":"Tutorial","size":25},{"classNo":"E1","startTime":"1800","endTime":"2000","weeks":[4,6,8,10,12],"venue":"AS3-0303","day":"Monday","lessonType":"Tutorial","size":25},{"classNo":"E5","startTime":"1600","endTime":"1800","weeks":[4,6,8,10,12],"venue":"AS1-0203","day":"Thursday","lessonType":"Tutorial","size":25},{"classNo":"D2","startTime":"0800","endTime":"1000","weeks":[3,5,7,9,11],"venue":"","day":"Tuesday","lessonType":"Tutorial","size":25},{"classNo":"1","startTime":"0800","endTime":"1000","weeks":[1,2,3,4,5,6,7,8,9,10,11,12,13],"venue":"","day":"Friday","lessonType":"Lecture","size":350},{"classNo":"D7","startTime":"0800","endTime":"1000","weeks":[3,5,7,9,11],"venue":"AS1-0209","day":"Monday","lessonType":"Tutorial","size":25},{"classNo":"E2","startTime":"0800","endTime":"1000","weeks":[4,6,8,10,12],"venue":"AS3-0214","day":"Tuesday","lessonType":"Tutorial","size":25},{"classNo":"D6","startTime":"1200","endTime":"1400","weeks":[3,5,7,9,11],"venue":"","day":"Friday","lessonType":"Tutorial","size":25},{"classNo":"D1","startTime":"1800","endTime":"2000","weeks":[3,5,7,9,11],"venue":"AS1-0208","day":"Monday","lessonType":"Tutorial","size":25},{"classNo":"D4","startTime":"1600","endTime":"1800","weeks":[3,5,7,9,11],"venue":"AS1-0207","day":"Wednesday","lessonType":"Tutorial","size":25},{"classNo":"D5","startTime":"1600","endTime":"1800","weeks":[3,5,7,9,11],"venue":"","day":"Thursday","lessonType":"Tutorial","size":25},{"classNo":"E4","startTime":"1600","endTime":"1800","weeks":[4,6,8,10,12],"venue":"","day":"Wednesday","lessonType":"Tutorial","size":25}]},{"semester":4,"timetable":[{"classNo":"1","startTime":"1000","endTime":"1300","weeks":{"start":"2020-06-23","end":"2020-07-21","weeks":[1,2,4,5]},"venue":"LT10","day":"Tuesday","lessonType":"Lecture","size":50},{"classNo":"1","startTime":"1000","endTime":"1300","weeks":{"start":"2020-06-24","end":"2020-07-22","weeks":[1,2,4,5]},"venue":"LT10","day":"Wednesday","lessonType":"Lecture","size":50},{"classNo":"1","startTime":"1000","endTime":"1300","weeks":{"start":"2020-06-26","end":"2020-07-24","weeks":[1,2,4,5]},"venue":"LT10","day":"Friday","lessonType":"Lecture","size":50}]}]}
