{"acadYear":"2019/2020","description":"This course is an introduction to Neo-Confucianism, one of the most influential intellectual movements in East Asia. Neo-Confucianism combines a profound metaphysics with a subtle theory of ethical cultivation. There is also discussion of Chinese Mahayana Buddhism, whose views of the self and ethics are the primary targets of the Neo-Confucian critique.","title":"Neo-Confucianism and Chinese Buddhism","department":"Yale-NUS College","faculty":"Yale-NUS College","workload":[0,3,0,0,9.5],"moduleCredit":"5","moduleCode":"YHU2287","semesterData":[{"semester":2,"timetable":[{"classNo":"1","startTime":"1430","endTime":"1600","weeks":[1,2,3,4,5,6,7,8,9,10,11,12,13],"venue":"Y-CR5","day":"Monday","lessonType":"Seminar-Style Module Class","size":18},{"classNo":"1","startTime":"1430","endTime":"1600","weeks":[1,2,3,4,5,6,7,8,9,10,11,12,13],"venue":"Y-CR5","day":"Thursday","lessonType":"Seminar-Style Module Class","size":18}]}]}
