{"acadYear":"2019/2020","preclusion":"YHU1211 (previous module code)","description":"This module will thoroughly examine Japan’s most celebrated artistic medium from the mid-17th century to the modern era. Along with close studies of technological developments, major genres, and master printmakers, the module will explore complex issues of urban culture, print capitalism, censorship, representation of war and national identity, gender roles, and portrayals of modernization.","title":"Japanese Woodblock Prints","department":"Yale-NUS College","faculty":"Yale-NUS College","workload":[0,3,0,0,9.5],"moduleCredit":"5","moduleCode":"YHU3293","semesterData":[{"semester":1,"timetable":[{"classNo":"1","startTime":"1300","endTime":"1430","weeks":[1,2,3,4,5,6,7,8,9,10,11,12,13],"venue":"Y-GLRm2","day":"Monday","lessonType":"Seminar-Style Module Class","size":18},{"classNo":"1","startTime":"1300","endTime":"1430","weeks":[1,2,3,4,5,6,7,8,9,10,11,12,13],"venue":"Y-GLRm2","day":"Thursday","lessonType":"Seminar-Style Module Class","size":18}]}],"fulfillRequirements":["YHU4207"]}
